cmdorc_frontend/__init__.py
cmdorc_frontend/config.py
cmdorc_frontend/config_discovery.py
cmdorc_frontend/file_watcher.py
cmdorc_frontend/models.py
cmdorc_frontend/multiconfig.py
cmdorc_frontend/notifier.py
cmdorc_frontend/orchestrator_adapter.py
cmdorc_frontend/watchers.py
textual_cmdorc-0.1.0.dist-info/METADATA
textual_cmdorc-0.1.0.dist-info/WHEEL
textual_cmdorc-0.1.0.dist-info/entry_points.txt
textual_cmdorc-0.1.0.dist-info/licenses/LICENSE
textual_cmdorc/__init__.py
textual_cmdorc/cli.py
textual_cmdorc/cmdorc_app.py
textual_cmdorc/config_switcher.py
textual_cmdorc/details_screen.py
textual_cmdorc/file_separator.py
textual_cmdorc/formatting.py
textual_cmdorc/logging.py
textual_cmdorc/setup_screen.py
textual_cmdorc/tooltip_builders.py
textual_cmdorc/tooltips.md
textual_cmdorc/watcher_status_line.py
textual_cmdorc-0.1.0.dist-info/RECORD
