Metadata-Version: 2.1
Name: textual-cmdorc
Version: 0.1.0
Summary: Embeddable TUI frontend for cmdorc command orchestration with real-time status, keyboard shortcuts, and trigger chains.
Keywords: textual,tui,terminal,cmdorc,orchestration,command-execution,automation,developer-tools,monitoring,embeddable
Author-Email: eyecantell <paul@pneuma.solutions>
License: MIT
Classifier: Development Status :: 4 - Beta
Classifier: Environment :: Console
Classifier: Intended Audience :: Developers
Classifier: License :: OSI Approved :: MIT License
Classifier: Operating System :: OS Independent
Classifier: Programming Language :: Python :: 3
Classifier: Programming Language :: Python :: 3.10
Classifier: Programming Language :: Python :: 3.11
Classifier: Programming Language :: Python :: 3.12
Classifier: Programming Language :: Python :: 3.13
Classifier: Topic :: Software Development :: Libraries :: Python Modules
Classifier: Topic :: Terminals
Classifier: Topic :: Software Development :: User Interfaces
Project-URL: Homepage, https://github.com/eyecantell/textual-cmdorc
Project-URL: Repository, https://github.com/eyecantell/textual-cmdorc
Project-URL: Issues, https://github.com/eyecantell/textual-cmdorc/issues
Project-URL: Documentation, https://github.com/eyecantell/textual-cmdorc#readme
Project-URL: Changelog, https://github.com/eyecantell/textual-cmdorc/releases
Requires-Python: >=3.10
Requires-Dist: textual>=6.6.0
Requires-Dist: cmdorc>=0.11.0
Requires-Dist: watchdog>=4.0.0
Requires-Dist: textual-filelink>=0.10.1
Requires-Dist: tomli>=2.0.0; python_version < "3.11"
